omilayers/__init__.py
omilayers/core/__init__.py
omilayers/core/dbclass.py
omilayers/engines/__init__.py
omilayers/engines/duckdb/__init__.py
omilayers/engines/duckdb/dbclass.py
omilayers/engines/sqlite/__init__.py
omilayers/engines/sqlite/dbclass.py
omilayers/utils/__init__.py
omilayers-0.2.3.dist-info/LICENSE
omilayers-0.2.3.dist-info/METADATA
omilayers-0.2.3.dist-info/WHEEL
omilayers-0.2.3.dist-info/top_level.txt
omilayers-0.2.3.dist-info/RECORD
