Metadata-Version: 2.1
Name: omilayers
Version: 0.2.3
Summary: A SQLite and DuckDB wrapper suitable for bioinformatic analysis of multi-omic data.
Author: Dimitrios Kioroglou
Author-email: <d.kioroglou@hotmail.com>
License: CC-BY-4.0
Keywords: duckdb,sqlite3,omics,bioinformatics,data analysis
Classifier: Development Status :: 1 - Planning
Classifier: Intended Audience :: Science/Research
Classifier: Programming Language :: Python :: 3
Classifier: Operating System :: Unix
Classifier: Operating System :: MacOS :: MacOS X
Classifier: Operating System :: Microsoft :: Windows
License-File: LICENSE
Requires-Dist: duckdb>=0.10.2
Requires-Dist: pandas
Requires-Dist: numpy
